{
  "title": "OpenConvenanten",
  "description": "",
  "labelPlacement": "top_label",
  "descriptionPlacement": "below",
  "button": {
    "type": "text",
    "text": "Versturen",
    "imageUrl": "",
    "width": "auto",
    "location": "bottom",
    "layoutGridColumnSpan": 12,
    "id": "submit"
  },
  "fields": [
    {
      "type": "text",
      "label": "Zaaknummer (ID)",
      "adminLabel": "",
      "isRequired": false,
      "size": "large",
      "errorMessage": "",
      "visibility": "visible",
      "inputs": null,
      "description": "Laat leeg om automatisch te genereren",
      "allowsPrepopulate": false,
      "inputMask": false,
      "inputMaskValue": "",
      "inputMaskIsCustom": false,
      "maxLength": "",
      "inputType": "",
      "labelPlacement": "",
      "descriptionPlacement": "",
      "subLabelPlacement": "",
      "placeholder": "",
      "cssClass": "",
      "inputName": "",
      "noDuplicates": false,
      "defaultValue": "",
      "enableAutocomplete": false,
      "autocompleteAttribute": "",
      "choices": "",
      "conditionalLogic": "",
      "productField": "",
      "layoutGridColumnSpan": "",
      "enablePasswordInput": "",
      "enableEnhancedUI": 0,
      "layoutGroupId": "8b9d03ab",
      "multipleFiles": false,
      "maxFiles": "",
      "calculationFormula": "",
      "calculationRounding": "",
      "enableCalculation": "",
      "disableQuantity": false,
      "displayAllCategories": false,
      "useRichTextEditor": false,
      "errors": [],
      "fields": "",
      "formId": 4,
      "id": 6,
      "displayOnly": "",
      "checkboxLabel": ""
    },
    {
      "type": "text",
      "id": 17,
      "formId": 4,
      "label": "Titel",
      "adminLabel": "",
      "isRequired": true,
      "size": "large",
      "errorMessage": "",
      "visibility": "visible",
      "inputs": null,
      "description": "",
      "allowsPrepopulate": false,
      "inputMask": false,
      "inputMaskValue": "",
      "inputMaskIsCustom": false,
      "maxLength": "",
      "inputType": "",
      "labelPlacement": "",
      "descriptionPlacement": "",
      "subLabelPlacement": "",
      "placeholder": "",
      "cssClass": "",
      "inputName": "",
      "noDuplicates": false,
      "defaultValue": "",
      "enableAutocomplete": false,
      "autocompleteAttribute": "",
      "choices": "",
      "conditionalLogic": "",
      "productField": "",
      "layoutGridColumnSpan": 12,
      "enablePasswordInput": "",
      "enableEnhancedUI": 0,
      "layoutGroupId": "1d231bec",
      "multipleFiles": false,
      "maxFiles": "",
      "calculationFormula": "",
      "calculationRounding": "",
      "enableCalculation": "",
      "disableQuantity": false,
      "displayAllCategories": false,
      "useRichTextEditor": false,
      "errors": [],
      "fields": "",
      "displayOnly": ""
    },
    {
      "type": "textarea",
      "id": 5,
      "label": "Samenvatting",
      "adminLabel": "",
      "isRequired": false,
      "size": "large",
      "errorMessage": "",
      "visibility": "visible",
      "inputs": null,
      "description": "",
      "allowsPrepopulate": false,
      "inputMask": false,
      "inputMaskValue": "",
      "inputMaskIsCustom": false,
      "maxLength": "",
      "inputType": "",
      "labelPlacement": "",
      "descriptionPlacement": "",
      "subLabelPlacement": "",
      "placeholder": "",
      "cssClass": "",
      "inputName": "",
      "noDuplicates": false,
      "defaultValue": "",
      "enableAutocomplete": false,
      "autocompleteAttribute": "",
      "choices": "",
      "conditionalLogic": "",
      "productField": "",
      "layoutGridColumnSpan": "",
      "form_id": "",
      "useRichTextEditor": false,
      "enableEnhancedUI": 0,
      "layoutGroupId": "d6421318",
      "multipleFiles": false,
      "maxFiles": "",
      "calculationFormula": "",
      "calculationRounding": "",
      "enableCalculation": "",
      "disableQuantity": false,
      "displayAllCategories": false,
      "errors": [],
      "fields": "",
      "formId": 4,
      "displayOnly": ""
    },
    {
      "type": "text",
      "label": "Partijen",
      "adminLabel": "",
      "isRequired": false,
      "size": "large",
      "errorMessage": "",
      "visibility": "visible",
      "inputs": null,
      "description": "Gebruik een komma (,) om meerdere partijen in de voeren",
      "allowsPrepopulate": false,
      "inputMask": false,
      "inputMaskValue": "",
      "inputMaskIsCustom": false,
      "maxLength": "",
      "inputType": "",
      "labelPlacement": "",
      "descriptionPlacement": "",
      "subLabelPlacement": "",
      "placeholder": "",
      "cssClass": "",
      "inputName": "",
      "noDuplicates": false,
      "defaultValue": "",
      "enableAutocomplete": false,
      "autocompleteAttribute": "",
      "choices": "",
      "conditionalLogic": "",
      "productField": "",
      "layoutGridColumnSpan": 12,
      "enablePasswordInput": "",
      "enableEnhancedUI": 0,
      "layoutGroupId": "082eb434",
      "multipleFiles": false,
      "maxFiles": "",
      "calculationFormula": "",
      "calculationRounding": "",
      "enableCalculation": "",
      "disableQuantity": false,
      "displayAllCategories": false,
      "useRichTextEditor": false,
      "errors": [],
      "fields": "",
      "formId": 4,
      "id": 7,
      "displayOnly": ""
    },
    {
      "type": "text",
      "label": "Onderwerp",
      "adminLabel": "",
      "isRequired": true,
      "size": "large",
      "errorMessage": "",
      "visibility": "visible",
      "inputs": null,
      "description": "",
      "allowsPrepopulate": false,
      "inputMask": false,
      "inputMaskValue": "",
      "inputMaskIsCustom": false,
      "maxLength": "",
      "inputType": "",
      "labelPlacement": "",
      "descriptionPlacement": "",
      "subLabelPlacement": "",
      "placeholder": "",
      "cssClass": "",
      "inputName": "",
      "noDuplicates": false,
      "defaultValue": "",
      "enableAutocomplete": false,
      "autocompleteAttribute": "",
      "choices": "",
      "conditionalLogic": "",
      "productField": "",
      "layoutGridColumnSpan": "",
      "enablePasswordInput": "",
      "enableEnhancedUI": 0,
      "layoutGroupId": "d90f6358",
      "multipleFiles": false,
      "maxFiles": "",
      "calculationFormula": "",
      "calculationRounding": "",
      "enableCalculation": "",
      "disableQuantity": false,
      "displayAllCategories": false,
      "useRichTextEditor": false,
      "errors": [],
      "fields": "",
      "formId": 4,
      "id": 8,
      "displayOnly": ""
    },
    {
      "type": "select",
      "label": "Beleidsterrein",
      "adminLabel": "",
      "isRequired": true,
      "size": "large",
      "errorMessage": "",
      "visibility": "visible",
      "inputs": null,
      "choices": [
        {
          "text": "Economie",
          "value": "Economie",
          "isSelected": false,
          "price": ""
        },
        {
          "text": "Onderwijs",
          "value": "Onderwijs",
          "isSelected": false,
          "price": ""
        },
        {
          "text": "Wonen",
          "value": "Wonen",
          "isSelected": false,
          "price": ""
        },
        { "text": "Zorg", "value": "Zorg", "isSelected": false, "price": "" },
        {
          "text": "Veiligheid",
          "value": "Veiligheid",
          "isSelected": false,
          "price": ""
        },
        {
          "text": "Ruimte",
          "value": "Ruimte",
          "isSelected": false,
          "price": ""
        },
        {
          "text": "Cultuur",
          "value": "Cultuur",
          "isSelected": false,
          "price": ""
        },
        {
          "text": "Sport",
          "value": "Sport",
          "isSelected": false,
          "price": ""
        },
        {
          "text": "Milieu",
          "value": "Milieu",
          "isSelected": false,
          "price": ""
        },
        {
          "text": "Overig",
          "value": "Overig",
          "isSelected": false,
          "price": ""
        }
      ],
      "description": "Dit zijn voorbeeldopties",
      "allowsPrepopulate": false,
      "inputMask": false,
      "inputMaskValue": "",
      "inputMaskIsCustom": false,
      "maxLength": "",
      "inputType": "",
      "labelPlacement": "",
      "descriptionPlacement": "",
      "subLabelPlacement": "",
      "placeholder": "",
      "cssClass": "",
      "inputName": "",
      "noDuplicates": false,
      "defaultValue": "",
      "enableAutocomplete": false,
      "autocompleteAttribute": "",
      "conditionalLogic": "",
      "productField": "",
      "layoutGridColumnSpan": "",
      "enablePrice": "",
      "enableEnhancedUI": 0,
      "layoutGroupId": "f96335eb",
      "multipleFiles": false,
      "maxFiles": "",
      "calculationFormula": "",
      "calculationRounding": "",
      "enableCalculation": "",
      "disableQuantity": false,
      "displayAllCategories": false,
      "useRichTextEditor": false,
      "errors": [],
      "checkboxLabel": "",
      "fields": "",
      "formId": 4,
      "id": 9,
      "displayOnly": ""
    },
    {
      "type": "text",
      "id": 16,
      "formId": 4,
      "label": "Duur",
      "adminLabel": "",
      "isRequired": true,
      "size": "large",
      "errorMessage": "",
      "visibility": "visible",
      "inputs": null,
      "description": "",
      "allowsPrepopulate": false,
      "inputMask": false,
      "inputMaskValue": "",
      "inputMaskIsCustom": false,
      "maxLength": "",
      "inputType": "",
      "labelPlacement": "",
      "descriptionPlacement": "",
      "subLabelPlacement": "",
      "placeholder": "",
      "cssClass": "",
      "inputName": "",
      "noDuplicates": false,
      "defaultValue": "",
      "enableAutocomplete": false,
      "autocompleteAttribute": "",
      "choices": "",
      "conditionalLogic": "",
      "productField": "",
      "layoutGridColumnSpan": 12,
      "enablePasswordInput": "",
      "enableEnhancedUI": 0,
      "layoutGroupId": "b529e4a5",
      "multipleFiles": false,
      "maxFiles": "",
      "calculationFormula": "",
      "calculationRounding": "",
      "enableCalculation": "",
      "disableQuantity": false,
      "displayAllCategories": false,
      "useRichTextEditor": false,
      "errors": [],
      "fields": "",
      "displayOnly": ""
    },
    {
      "type": "date",
      "label": "Datum ondertekening",
      "adminLabel": "",
      "isRequired": true,
      "size": "large",
      "errorMessage": "",
      "visibility": "visible",
      "inputs": null,
      "dateType": "datepicker",
      "dateFormat": "mdy",
      "dateFormatPlacement": "below",
      "calendarIconType": "none",
      "description": "",
      "allowsPrepopulate": false,
      "inputMask": false,
      "inputMaskValue": "",
      "inputMaskIsCustom": false,
      "maxLength": "",
      "inputType": "",
      "labelPlacement": "",
      "descriptionPlacement": "",
      "subLabelPlacement": "",
      "placeholder": "",
      "cssClass": "",
      "inputName": "",
      "noDuplicates": false,
      "defaultValue": "",
      "enableAutocomplete": false,
      "autocompleteAttribute": "",
      "choices": "",
      "conditionalLogic": "",
      "calendarIconUrl": "",
      "productField": "",
      "layoutGridColumnSpan": "",
      "enableEnhancedUI": 0,
      "layoutGroupId": "98822562",
      "multipleFiles": false,
      "maxFiles": "",
      "calculationFormula": "",
      "calculationRounding": "",
      "enableCalculation": "",
      "disableQuantity": false,
      "displayAllCategories": false,
      "useRichTextEditor": false,
      "errors": [],
      "fields": "",
      "formId": 4,
      "id": 11,
      "displayOnly": ""
    },
    {
      "type": "textarea",
      "label": "Inhoud",
      "adminLabel": "",
      "isRequired": false,
      "size": "large",
      "errorMessage": "",
      "visibility": "visible",
      "inputs": null,
      "description": "",
      "allowsPrepopulate": false,
      "inputMask": false,
      "inputMaskValue": "",
      "inputMaskIsCustom": false,
      "maxLength": "",
      "inputType": "",
      "labelPlacement": "",
      "descriptionPlacement": "",
      "subLabelPlacement": "",
      "placeholder": "",
      "cssClass": "",
      "inputName": "",
      "noDuplicates": false,
      "defaultValue": "",
      "enableAutocomplete": false,
      "autocompleteAttribute": "",
      "choices": "",
      "conditionalLogic": "",
      "productField": "",
      "layoutGridColumnSpan": "",
      "form_id": "",
      "useRichTextEditor": false,
      "enableEnhancedUI": 0,
      "layoutGroupId": "b312d374",
      "multipleFiles": false,
      "maxFiles": "",
      "calculationFormula": "",
      "calculationRounding": "",
      "enableCalculation": "",
      "disableQuantity": false,
      "displayAllCategories": false,
      "errors": [],
      "fields": "",
      "formId": 4,
      "id": 12,
      "displayOnly": ""
    },
    {
      "type": "fileupload",
      "id": 15,
      "formId": 4,
      "label": "Bijlagen (bestanden)",
      "adminLabel": "",
      "isRequired": false,
      "size": "large",
      "errorMessage": "",
      "visibility": "visible",
      "inputs": null,
      "description": "",
      "allowsPrepopulate": false,
      "inputMask": false,
      "inputMaskValue": "",
      "inputMaskIsCustom": false,
      "maxLength": "",
      "inputType": "",
      "labelPlacement": "",
      "descriptionPlacement": "",
      "subLabelPlacement": "",
      "placeholder": "",
      "cssClass": "",
      "inputName": "",
      "noDuplicates": false,
      "defaultValue": "",
      "enableAutocomplete": false,
      "autocompleteAttribute": "",
      "choices": "",
      "conditionalLogic": "",
      "maxFileSize": "",
      "maxFiles": "25",
      "multipleFiles": true,
      "allowedExtensions": "png, jpg, jpeg, pdf, docx, doc",
      "productField": "",
      "layoutGridColumnSpan": 12,
      "enableEnhancedUI": 0,
      "layoutGroupId": "b8e78f7d",
      "calculationFormula": "",
      "calculationRounding": "",
      "enableCalculation": "",
      "disableQuantity": false,
      "displayAllCategories": false,
      "useRichTextEditor": false,
      "checkboxLabel": "",
      "errors": [],
      "fields": "",
      "displayOnly": ""
    },
    {
      "type": "repeater",
      "label": "Bijlage URLS",
      "adminLabel": "",
      "isRequired": true,
      "size": "large",
      "errorMessage": "",
      "visibility": "visible",
      "inputs": null,
      "description": "",
      "allowsPrepopulate": false,
      "inputMask": false,
      "inputMaskValue": "",
      "inputMaskIsCustom": false,
      "maxLength": "",
      "inputType": "",
      "labelPlacement": "",
      "descriptionPlacement": "",
      "subLabelPlacement": "",
      "placeholder": "",
      "cssClass": "",
      "inputName": "",
      "noDuplicates": false,
      "defaultValue": "",
      "enableAutocomplete": false,
      "autocompleteAttribute": "",
      "choices": "",
      "conditionalLogic": "",
      "productField": "",
      "layoutGridColumnSpan": 12,
      "enablePasswordInput": "",
      "enableEnhancedUI": 0,
      "layoutGroupId": "e82b3ad4",
      "multipleFiles": false,
      "maxFiles": "",
      "calculationFormula": "",
      "calculationRounding": "",
      "enableCalculation": "",
      "disableQuantity": false,
      "displayAllCategories": false,
      "useRichTextEditor": false,
      "errors": [],
      "fields": [
        {
          "type": "text",
          "label": "URL Bijlage",
          "adminLabel": "",
          "isRequired": false,
          "size": "large",
          "errorMessage": "",
          "visibility": "visible",
          "inputs": null,
          "description": "",
          "allowsPrepopulate": false,
          "inputMask": false,
          "inputMaskValue": "",
          "inputMaskIsCustom": false,
          "maxLength": "",
          "inputType": "",
          "labelPlacement": "",
          "descriptionPlacement": "",
          "subLabelPlacement": "",
          "placeholder": "https://",
          "cssClass": "",
          "inputName": "",
          "noDuplicates": false,
          "defaultValue": "",
          "enableAutocomplete": false,
          "autocompleteAttribute": "",
          "choices": "",
          "productField": "",
          "layoutGridColumnSpan": 6,
          "enablePasswordInput": "",
          "enableEnhancedUI": 0,
          "layoutGroupId": "e104d8b2",
          "multipleFiles": false,
          "maxFiles": "",
          "calculationFormula": "",
          "calculationRounding": "",
          "enableCalculation": "",
          "disableQuantity": false,
          "displayAllCategories": false,
          "useRichTextEditor": false,
          "errors": [],
          "fields": "",
          "layoutSpacerGridColumnSpan": 0,
          "formId": 4,
          "pageNumber": 1,
          "id": 14
        }
      ],
      "formId": 4,
      "nestingLevel": 0,
      "id": 13,
      "displayOnly": ""
    }
  ],
  "version": "2.6.8",
  "markupVersion": 2,
  "useCurrentUserAsAuthor": true,
  "postContentTemplateEnabled": false,
  "postTitleTemplateEnabled": false,
  "postTitleTemplate": "",
  "postContentTemplate": "",
  "lastPageButton": null,
  "pagination": null,
  "firstPageCssClass": null,
  "nextFieldId": 18,
  "is_active": "1",
  "is_trash": "0",
  "notifications": [
    {
      "id": "63aac68b240b0",
      "isActive": true,
      "to": "{admin_email}",
      "name": "Beheerdersmelding",
      "event": "form_submission",
      "toType": "email",
      "subject": "Nieuwe inzending van {form_title}",
      "message": "{all_fields}"
    }
  ],
  "confirmations": [
    {
      "id": "63aac68b24263",
      "name": "Standaardbevestiging",
      "isDefault": true,
      "type": "message",
      "message": "Bedankt voor je bericht! We zullen binnenkort contact met je opnemen.",
      "url": "",
      "pageId": "",
      "queryString": ""
    }
  ],
  "subLabelPlacement": "below",
  "requiredIndicator": "text",
  "customRequiredIndicator": "(Vereist)",
  "cssClass": "",
  "saveButtonText": "Opslaan en later doorgaan",
  "limitEntries": false,
  "limitEntriesCount": "",
  "limitEntriesPeriod": "",
  "limitEntriesMessage": "",
  "scheduleForm": false,
  "scheduleStart": "",
  "scheduleEnd": "",
  "schedulePendingMessage": "",
  "scheduleMessage": "",
  "requireLogin": false,
  "requireLoginMessage": "",
  "validationSummary": false,
  "deprecated": "",
  "saveEnabled": "",
  "enableHoneypot": false,
  "enableAnimation": false,
  "save": {
    "enabled": false,
    "button": { "type": "link", "text": "Opslaan en later doorgaan" }
  },
  "scheduleStartHour": "",
  "scheduleStartMinute": "",
  "scheduleStartAmpm": "",
  "scheduleEndHour": "",
  "scheduleEndMinute": "",
  "scheduleEndAmpm": "",
  "feeds": {}
}
